velero/__init__.py
velero/auth.py
velero/models.py
velero/utils.py
velero/libs/__init__.py
velero/static/css/dataTables.min.css
velero/static/css/prism.css
velero/static/css/tabler_datatable.css
velero/static/css/bootstrap-toggle/css/bootstrap4-toggle.css
velero/static/css/bootstrap-toggle/css/bootstrap4-toggle.min.css
velero/static/css/choices/choices.min.css
velero/static/css/slider/ion.rangeSlider.min.css
velero/static/css/tabler/demo.css
velero/static/css/tabler/demo.css.map
velero/static/css/tabler/demo.min.css
velero/static/css/tabler/demo.min.css.map
velero/static/css/tabler/tabler-buttons.css
velero/static/css/tabler/tabler-buttons.css.map
velero/static/css/tabler/tabler-buttons.min.css
velero/static/css/tabler/tabler-buttons.min.css.map
velero/static/css/tabler/tabler-flags.css
velero/static/css/tabler/tabler-flags.css.map
velero/static/css/tabler/tabler-flags.min.css
velero/static/css/tabler/tabler-flags.min.css.map
velero/static/css/tabler/tabler-payments.css
velero/static/css/tabler/tabler-payments.css.map
velero/static/css/tabler/tabler-payments.min.css
velero/static/css/tabler/tabler-payments.min.css.map
velero/static/css/tabler/tabler.css
velero/static/css/tabler/tabler.css.map
velero/static/css/tabler/tabler.min.css
velero/static/css/tabler/tabler.min.css.map
velero/static/css/toastr/toastr.min.css
velero/static/img/auth.svg
velero/static/img/forbiden.svg
velero/static/img/page_not_found.svg
velero/static/img/search.svg
velero/static/img/velero_logo.svg
velero/static/img/velero_logo_white.svg
velero/static/img/flags/ad.svg
velero/static/img/flags/ae.svg
velero/static/img/flags/af.svg
velero/static/img/flags/ag.svg
velero/static/img/flags/ai.svg
velero/static/img/flags/al.svg
velero/static/img/flags/am.svg
velero/static/img/flags/ao.svg
velero/static/img/flags/aq.svg
velero/static/img/flags/ar.svg
velero/static/img/flags/as.svg
velero/static/img/flags/at.svg
velero/static/img/flags/au.svg
velero/static/img/flags/aw.svg
velero/static/img/flags/ax.svg
velero-0.1.1.dist-info/LICENSE
velero-0.1.1.dist-info/WHEEL
velero-0.1.1.dist-info/METADATA
velero-0.1.1.dist-info/RECORD
