Metadata-Version: 2.1
Name: velero
Version: 0.1.1
Summary: An amazing sample package!
Author-email: Denis Tu <dmarshaltu@gmail.com>
Classifier: License :: OSI Approved :: MIT License
Project-URL: Home, https://github.com/DmarshalTU/velero_wui_py
